odoo/addons/crm_lead_personal_file_data/CHANGELOG.md
odoo/addons/crm_lead_personal_file_data/README.rst
odoo/addons/crm_lead_personal_file_data/__init__.py
odoo/addons/crm_lead_personal_file_data/__manifest__.py
odoo/addons/crm_lead_personal_file_data/data/dms_category.xml
odoo/addons/crm_lead_personal_file_data/data/dms_directory.xml
odoo/addons/crm_lead_personal_file_data/data/dms_storage.xml
odoo/addons/crm_lead_personal_file_data/i18n/ca_ES.po
odoo/addons/crm_lead_personal_file_data/i18n/es.po
odoo/addons/crm_lead_personal_file_data/listeners/__init__.py
odoo/addons/crm_lead_personal_file_data/listeners/crm_lead_listener.py
odoo/addons/crm_lead_personal_file_data/listeners/dms_file_listener.py
odoo/addons/crm_lead_personal_file_data/models/__init__.py
odoo/addons/crm_lead_personal_file_data/models/dms_directory.py
odoo/addons/crm_lead_personal_file_data/static/description/icon.png
odoo/addons/crm_lead_personal_file_data/tests/__init__.py
odoo/addons/crm_lead_personal_file_data/tests/listeners/__init__.py
odoo/addons/crm_lead_personal_file_data/tests/listeners/test_crm_lead_listener.py
odoo/addons/crm_lead_personal_file_data/tests/listeners/test_dms_file_listener.py
odoo/addons/crm_lead_personal_file_data/tests/models/__init__.py
odoo/addons/crm_lead_personal_file_data/tests/models/test_dms_directory.py
odoo/addons/crm_lead_personal_file_data/views/crm_lead_views.xml
odoo12_addon_crm_lead_personal_file_data-12.0.0.1.0.dist-info/METADATA
odoo12_addon_crm_lead_personal_file_data-12.0.0.1.0.dist-info/WHEEL
odoo12_addon_crm_lead_personal_file_data-12.0.0.1.0.dist-info/top_level.txt
odoo12_addon_crm_lead_personal_file_data-12.0.0.1.0.dist-info/RECORD
