Metadata-Version: 2.1
Name: odoo12-addon-crm-lead-personal-file-data
Version: 12.0.0.1.0
Summary: Move lead pending assigned files to its partner directory under personal data.
Home-page: https://gitlab.com/somitcoop/erp-research/odoo-helpdesk
Author: Som It Cooperatiu SCCL, Som Connexió SCCL,
License: AGPL-3
Platform: UNKNOWN
Classifier: Programming Language :: Python
Classifier: Framework :: Odoo
Classifier: Framework :: Odoo :: 12.0
Classifier: License :: OSI Approved :: GNU Affero General Public License v3
Requires-Python: >=3.5
Requires-Dist: odoo12-addon-dms-res-model-root-directory
Requires-Dist: odoo <12.1dev,>=12.0a
